found_CLI_tools/__init__.py
found_CLI_tools/attitude/__init__.py
found_CLI_tools/attitude/constants.py
found_CLI_tools/attitude/main.py
found_CLI_tools/attitude/transform.py
found_tools-0.0.0.dist-info/METADATA
found_tools-0.0.0.dist-info/WHEEL
found_tools-0.0.0.dist-info/entry_points.txt
found_tools-0.0.0.dist-info/top_level.txt
found_tools-0.0.0.dist-info/RECORD
