Metadata-Version: 2.4
Name: found-tools
Version: 0.0.0
Summary: Add your description here
Requires-Python: >=3.14
Requires-Dist: scipy>=1.16.3
